envcrypted/__init__.py
envcrypted/__main__.py
envcrypted/exceptions.py
envcrypted-0.0.2.dist-info/METADATA
envcrypted-0.0.2.dist-info/WHEEL
envcrypted-0.0.2.dist-info/entry_points.txt
envcrypted-0.0.2.dist-info/licenses/LICENSE.txt
envcrypted-0.0.2.dist-info/RECORD
