Metadata-Version: 2.3
Name: EnvCrypted
Version: 0.0.2
Summary: EnvCrypted is a high-performance Python 3.12+ package that encrypts all environment variables using age encryption with ephemeral keys generated at runtime. (Note: This package is highly experimental!)
Author-email: Alchemyst0x <alchemyst@blockmage.dev>
License: Apache-2.0
License-File: LICENSE.txt
Requires-Python: >=3.12
Requires-Dist: pyrage-stubs>=1.2.3
Requires-Dist: pyrage>=1.2.1
Requires-Dist: python-dotenv>=1.0.1
Provides-Extra: onepassword
Requires-Dist: onepassword-sdk>=0.1.3; extra == 'onepassword'
Requires-Dist: pydantic-settings>=2.6.1; extra == 'onepassword'
Requires-Dist: pydantic>=2.9.2; extra == 'onepassword'
